[
    {
        "Path": "https://d3dg8a58k5opnp.cloudfront.net/- sept 08_Trim.mp4",
        "Title": "Summer Adventures",
        "Categories": "Summer, Vacation",
        "Description": "Fun in the sun!",
        "Thumbnail": "https://d3dg8a58k5opnp.cloudfront.net/- sept 08_Trim.jpg",
        "Subtitles": "https://gist.githubusercontent.com/BrenanMarenger/15f4299d82dec6c8843040825d5b1517/raw/d0f02d88b05b23911f87024f9c80a15b90f4e53d/gistfile1.txt",
        "Year": 2008
    },
    {
        "Path": "https://d3dg8a58k5opnp.cloudfront.net/3.03 - 6.03_Trim.mp4",
        "Title": "Pennsylvania Trip",
        "Categories": "Family, Vacation",
        "Description": "Trampoline Earthquake!",
        "Thumbnail": "https://d3dg8a58k5opnp.cloudfront.net/3.03 - 6.03_Trim.jpg",
        "Subtitles": "https://gist.githubusercontent.com/BrenanMarenger/9ae438cecc76efe0caaeb34e6601697e/raw/c8f06539d7f1745d4bb6790f51c8ea57f94c0bc1/3.03%2520-%25206.03",
        "Year": 2003
    },
    {
        "Path": "https://d3dg8a58k5opnp.cloudfront.net/3.10-4.4.10_Trim.mp4",
        "Title": "Easter '10",
        "Categories": "Family, Holiday",
        "Description": "What did the Easter bunny leave?",
        "Thumbnail": "https://d3dg8a58k5opnp.cloudfront.net/3.10-4.4.10_Trim.jpg",
        "Subtitles": "https://gist.githubusercontent.com/BrenanMarenger/9ae438cecc76efe0caaeb34e6601697e/raw/c8f06539d7f1745d4bb6790f51c8ea57f94c0bc1/3.10-4.4.10_Trim.mp4.vtt",
        "Year": 2010
    },
    {
        "Path": "https://d3dg8a58k5opnp.cloudfront.net/4.06-8.06_Trim.mp4",
        "Title": "Bowling Alley Party",
        "Categories": "Birthday",
        "Description": "Tyler's 8th birthday party with friends",
        "Thumbnail": "https://d3dg8a58k5opnp.cloudfront.net/4.06-8.06_Trim.jpg",
        "Subtitles": "https://gist.githubusercontent.com/BrenanMarenger/9ae438cecc76efe0caaeb34e6601697e/raw/c8f06539d7f1745d4bb6790f51c8ea57f94c0bc1/4.06-8.06_Trim.mp4.vtt",
        "Year": 2006
    },
    {
        "Path": "https://d3dg8a58k5opnp.cloudfront.net/6.05 - 10.05_Trim.mp4",
        "Title": "Halloween '05",
        "Categories": "Holiday",
        "Description": "Ninja Lumberjack",
        "Thumbnail": "https://d3dg8a58k5opnp.cloudfront.net/6.05 - 10.05_Trim.jpg",
        "Subtitles": "https://gist.github.com/BrenanMarenger/9ae438cecc76efe0caaeb34e6601697e/raw/c8f06539d7f1745d4bb6790f51c8ea57f94c0bc1/6.05%2520-%252010.05",
        "Year": 2005
    },
    {
        "Path": "https://d3dg8a58k5opnp.cloudfront.net/6.05 - 10.05_Trim3.mp4",
        "Title": "Camp Fun",
        "Categories": "Summer, Vacation",
        "Description": "Fishing on the lake",
        "Thumbnail": "https://d3dg8a58k5opnp.cloudfront.net/6.05 - 10.05_Trim3.jpg",
        "Subtitles": "https://gist.github.com/BrenanMarenger/15f4299d82dec6c8843040825d5b1517/raw/b4cd0f7dedecf0371e96d4e6f94cd4f7f7a6c6f2/6.05%2520-%252010.05%25203",
        "Year": 2005
    },
    {
        "Path": "https://d3dg8a58k5opnp.cloudfront.net/7-2012_Trim.mp4",
        "Title": "Christmas '12",
        "Categories": "Winter, Holiday",
        "Description": "Did Santa drink his milk?",
        "Thumbnail": "https://d3dg8a58k5opnp.cloudfront.net/7-2012_Trim.jpg",
        "Subtitles": "https://gist.github.com/BrenanMarenger/d1277f6e09bc2d6a0ba5c977896867d4/raw/3fad77c622c919377124b4c193dddd3d96c96630/7-2012",
        "Year": 2012
    },
    {
        "Path": "https://d3dg8a58k5opnp.cloudfront.net/7-2012_Trim2.mp4",
        "Title": "Civir War!",
        "Categories": "Summer, Family",
        "Description": "5th grade confederate",
        "Thumbnail": "https://d3dg8a58k5opnp.cloudfront.net/7-2012_Trim2.jpg",
        "Subtitles": "",
        "Year": 2012
    },
    {
        "Path": "https://d3dg8a58k5opnp.cloudfront.net/8.04 - 1.05_Trim.mp4",
        "Title": "Spaghetti Fun",
        "Categories": "Summer, Holiday",
        "Description": "This is a normal evening with my family",
        "Thumbnail": "https://d3dg8a58k5opnp.cloudfront.net/8.04 - 1.05_Trim.jpg",
        "Subtitles": "https://gist.github.com/BrenanMarenger/d1277f6e09bc2d6a0ba5c977896867d4/raw/3fad77c622c919377124b4c193dddd3d96c96630/8.04%2520-%25201.05",
        "Year": 2004
    },
    {
        "Path": "https://d3dg8a58k5opnp.cloudfront.net/8.5.11-3.10.12_Trim.mp4",
        "Title": "Tyler's 13th Birthday",
        "Categories": "Summer, Birthday",
        "Description": "I'm just here for the bunny",
        "Thumbnail": "https://d3dg8a58k5opnp.cloudfront.net/8.5.11-3.10.12_Trim.jpg",
        "Subtitles": "https://gist.github.com/BrenanMarenger/d1277f6e09bc2d6a0ba5c977896867d4/raw/3fad77c622c919377124b4c193dddd3d96c96630/8.511-3.10.12",
        "Year": 2011
    },
    {
        "Path": "https://d3dg8a58k5opnp.cloudfront.net/12.06-3.07_Trim.mp4",
        "Title": "New Years '07",
        "Categories": "Holiday, Winter",
        "Description": "Happy New Yea- don't break anything!",
        "Thumbnail": "https://d3dg8a58k5opnp.cloudfront.net/12.06-3.07_Trim.jpg",
        "Subtitles": "https://gist.github.com/BrenanMarenger/d1277f6e09bc2d6a0ba5c977896867d4/raw/3fad77c622c919377124b4c193dddd3d96c96630/12.06-3.07_Trim.mp4.vtt",
        "Year": 2007
    },
    {
        "Path": "https://d3dg8a58k5opnp.cloudfront.net/12.15.05 - 4.06_Trim.mp4",
        "Title": "Christmas '05",
        "Categories": "Holiday, Winter",
        "Description": "Santa brought presents!",
        "Thumbnail": "https://d3dg8a58k5opnp.cloudfront.net/12.15.05 - 4.06.jpg",
        "Subtitles": "https://gist.github.com/BrenanMarenger/d1277f6e09bc2d6a0ba5c977896867d4/raw/3fad77c622c919377124b4c193dddd3d96c96630/12.15.05%2520-%25204.06_Trim.mp4.vtt",
        "Year": 2005
    },
    {
        "Path": "https://d3dg8a58k5opnp.cloudfront.net/Alexis kr grad_Trim.mp4",
        "Title": "Easter '09",
        "Categories": "Holiday",
        "Description": "Easter egg hunt!",
        "Thumbnail": "https://d3dg8a58k5opnp.cloudfront.net/Alexis kr grad_Trim.jpg",
        "Subtitles": "https://gist.github.com/BrenanMarenger/d1277f6e09bc2d6a0ba5c977896867d4/raw/3fad77c622c919377124b4c193dddd3d96c96630/Alexis%2520kr%2520grad_Trim.mp4.vtt",
        "Year": 2009
    },
    {
        "Path": "https://d3dg8a58k5opnp.cloudfront.net/Apr 04 - June 04_Trim.mp4",
        "Title": "Building Down!",
        "Categories": "Summer",
        "Description": "Building in my home town demolished",
        "Thumbnail": "https://d3dg8a58k5opnp.cloudfront.net/Apr 04 - June 04_Trim.jpg",
        "Subtitles": "https://gist.github.com/BrenanMarenger/d1277f6e09bc2d6a0ba5c977896867d4/raw/3fad77c622c919377124b4c193dddd3d96c96630/Apr%252004%2520-%2520June%252004_Trim.mp4.vtt",
        "Year": 2004
    },
    {
        "Path": "https://d3dg8a58k5opnp.cloudfront.net/april 2010-_Trim.mp4",
        "Title": "Easter '10",
        "Categories": "Holiday",
        "Description": "Egg decorations!",
        "Thumbnail": "https://d3dg8a58k5opnp.cloudfront.net/april 2010-_Trim.jpg",
        "Subtitles": "https://gist.github.com/BrenanMarenger/d1277f6e09bc2d6a0ba5c977896867d4/raw/3fad77c622c919377124b4c193dddd3d96c96630/april%25202010-_Trim.mp4.vtt",
        "Year": 2010
    },
    {
        "Path": "https://d3dg8a58k5opnp.cloudfront.net/april 2010-_Trim2.mp4",
        "Title": "Slip 'n Slide",
        "Categories": "Summer",
        "Description": "Coolest house in the neighborhood",
        "Thumbnail": "https://d3dg8a58k5opnp.cloudfront.net/april 2010-_Trim2.jpg",
        "Subtitles": "https://gist.github.com/BrenanMarenger/d1277f6e09bc2d6a0ba5c977896867d4/raw/3fad77c622c919377124b4c193dddd3d96c96630/april%25202010%25202",
        "Year": 2010
    },
    {
        "Path": "https://d3dg8a58k5opnp.cloudfront.net/dec 07 - mar 08_Trim.mp4",
        "Title": "Easter '08",
        "Categories": "Holiday",
        "Description": "I found an egg!",
        "Thumbnail": "https://d3dg8a58k5opnp.cloudfront.net/dec 07 - mar 08_Trim.jpg",
        "Subtitles": "https://gist.github.com/BrenanMarenger/d1277f6e09bc2d6a0ba5c977896867d4/raw/3fad77c622c919377124b4c193dddd3d96c96630/dec%252007%2520-mar%252008",
        "Year": 2008
    },
    {
        "Path": "https://d3dg8a58k5opnp.cloudfront.net/Dec 24, 2010_Trim.mp4",
        "Title": "Wisconsin Dell Waterpark",
        "Categories": "Vacation",
        "Description": "Surfs up!",
        "Thumbnail": "https://d3dg8a58k5opnp.cloudfront.net/Dec 24, 2010_Trim.jpg",
        "Subtitles": "https://gist.github.com/BrenanMarenger/d1277f6e09bc2d6a0ba5c977896867d4/raw/3fad77c622c919377124b4c193dddd3d96c96630/dec%252024,%25202010",
        "Year": 2010
    },
    {
        "Path": "https://d3dg8a58k5opnp.cloudfront.net/December 07_Trim.mp4",
        "Title": "Tyler's 9th Birthday/Christmas '07",
        "Categories": "Summer, Birthday, Family, Holiday, Winter",
        "Description": "Nutcracker!",
        "Thumbnail": "https://d3dg8a58k5opnp.cloudfront.net/December 07_Trim.jpg",
        "Subtitles": "https://gist.github.com/BrenanMarenger/d1277f6e09bc2d6a0ba5c977896867d4/raw/3fad77c622c919377124b4c193dddd3d96c96630/december%252007",
        "Year": 2009
    },
    {
        "Path": "https://d3dg8a58k5opnp.cloudfront.net/florida 09_Trim.mp4",
        "Title": "First Ocean Experience",
        "Categories": "Vacation",
        "Description": "Was that a shark?",
        "Thumbnail": "https://d3dg8a58k5opnp.cloudfront.net/florida 09_Trim.jpg",
        "Subtitles": "https://gist.github.com/BrenanMarenger/d1277f6e09bc2d6a0ba5c977896867d4/raw/3fad77c622c919377124b4c193dddd3d96c96630/florida%252009",
        "Year": 2009
    },
    {
        "Path": "https://d3dg8a58k5opnp.cloudfront.net/July 04 - Aug 04_Trim.mp4",
        "Title": "Waterpark Wonders",
        "Categories": "Summer, Vacation",
        "Description": "Cheeto's",
        "Thumbnail": "https://d3dg8a58k5opnp.cloudfront.net/July 04 - Aug 04_Trim.jpg",
        "Subtitles": "https://gist.github.com/BrenanMarenger/d1277f6e09bc2d6a0ba5c977896867d4/raw/3fad77c622c919377124b4c193dddd3d96c96630/july%252004%2520-%2520Aug%252004",
        "Year": 2004
    },
    {
        "Path": "https://d3dg8a58k5opnp.cloudfront.net/June 09 - Dec 09_Trim.mp4",
        "Title": "Bubble Bath Bonanza",
        "Categories": "Vacation, Family",
        "Description": "Three siblings end up in a foamy situation",
        "Thumbnail": "https://d3dg8a58k5opnp.cloudfront.net/June 09 - Dec 09_Trim.jpg",
        "Subtitles": "https://gist.github.com/BrenanMarenger/d1277f6e09bc2d6a0ba5c977896867d4/raw/3fad77c622c919377124b4c193dddd3d96c96630/June%252009%2520-%2520dec%252009",
        "Year": 2009
    },
    {
        "Path": "https://d3dg8a58k5opnp.cloudfront.net/New years 09_Trim.mp4",
        "Title": "Brenan's 9th Birthday",
        "Categories": "Birthday, Family",
        "Description": "I think he likes Starwars",
        "Thumbnail": "https://d3dg8a58k5opnp.cloudfront.net/New years 09_Trim.jpg",
        "Subtitles": "https://gist.github.com/BrenanMarenger/d1277f6e09bc2d6a0ba5c977896867d4/raw/3fad77c622c919377124b4c193dddd3d96c96630/New%2520years%252009",
        "Year": 2009
    },
    {
        "Path": "https://d3dg8a58k5opnp.cloudfront.net/Yard; Porc Pine Mts; Tyler 8m -12m_Trim.mp4",
        "Title": "The Bad Lands",
        "Categories": "Summer, Family",
        "Description": "Installing sprinklers, laying soil, and plantin' some grass",
        "Thumbnail": "https://d3dg8a58k5opnp.cloudfront.net/Yard; Porc Pine Mts; Tyler 8m -12m_Trim.jpg",
        "Subtitles": "https://gist.github.com/BrenanMarenger/d1277f6e09bc2d6a0ba5c977896867d4/raw/3fad77c622c919377124b4c193dddd3d96c96630/Yard",
        "Year": 1998
    }
]